ark/__init__.py
ark/asynco.py
ark_framework-0.0.4.dist-info/licenses/LICENSE
ark_framework-0.0.4.dist-info/METADATA
ark_framework-0.0.4.dist-info/WHEEL
ark_framework-0.0.4.dist-info/top_level.txt
ark_framework-0.0.4.dist-info/RECORD
