Metadata-Version: 2.4
Name: ark-framework
Version: 0.0.4
Summary: A lightweight async task framework using thread pools
Home-page: https://github.com/jobyywilson/ark-framework
Author: Joby Wilson Mathews
Author-email: jobyywilson@gmail.com
Classifier: Programming Language :: Python :: 3
Classifier: License :: OSI Approved :: MIT License
Classifier: Operating System :: OS Independent
Requires-Python: >=3.6
License-File: LICENSE
Dynamic: author
Dynamic: author-email
Dynamic: classifier
Dynamic: description
Dynamic: description-content-type
Dynamic: home-page
Dynamic: license-file
Dynamic: requires-python
Dynamic: summary
